comfospot40/__init__.py
comfospot40/packet.py
comfospot40/parser.py
comfospot40/state.py
pycomfospottwin40-0.2.0.dist-info/LICENSE
pycomfospottwin40-0.2.0.dist-info/METADATA
pycomfospottwin40-0.2.0.dist-info/WHEEL
pycomfospottwin40-0.2.0.dist-info/top_level.txt
pycomfospottwin40-0.2.0.dist-info/RECORD
