Metadata-Version: 2.1
Name: pycomfospottwin40
Version: 0.2.0
Summary: Read the Zehnder Comfospot Twin 40 status from Python.
Home-page: https://github.com/rubenbe/comfospottwin40
Author: rubenbe
Author-email: no@email.com
License: MIT
Download-URL: https://github.com/rubenbe/comfospottwin40/archive/0.2.0.zip
Keywords: zehnder iot homeautomation
Platform: UNKNOWN
Requires-Python: >=3.4
Provides-Extra: async
Requires-Dist: pyserial (==3.4) ; extra == 'async'
